snet_sdk-5.0.0-py3.11-nspkg.pth
snet/sdk/__init__.py
snet/sdk/account.py
snet/sdk/client_lib_generator.py
snet/sdk/concurrency_manager.py
snet/sdk/config.py
snet/sdk/custom_typing.py
snet/sdk/generic_client_interceptor.py
snet/sdk/service_client.py
snet/sdk/mpe/__init__.py
snet/sdk/mpe/mpe_contract.py
snet/sdk/mpe/payment_channel.py
snet/sdk/mpe/payment_channel_provider.py
snet/sdk/payment_strategies/__init__.py
snet/sdk/payment_strategies/default_payment_strategy.py
snet/sdk/payment_strategies/freecall_payment_strategy.py
snet/sdk/payment_strategies/paidcall_payment_strategy.py
snet/sdk/payment_strategies/payment_strategy.py
snet/sdk/payment_strategies/prepaid_payment_strategy.py
snet/sdk/payment_strategies/training_payment_strategy.py
snet/sdk/resources/package.json
snet/sdk/resources/root_certificate.py
snet/sdk/resources/proto/control_service.proto
snet/sdk/resources/proto/control_service_pb2.py
snet/sdk/resources/proto/control_service_pb2_grpc.py
snet/sdk/resources/proto/state_service.proto
snet/sdk/resources/proto/state_service_pb2.py
snet/sdk/resources/proto/state_service_pb2_grpc.py
snet/sdk/resources/proto/token_service.proto
snet/sdk/resources/proto/token_service_pb2.py
snet/sdk/resources/proto/token_service_pb2_grpc.py
snet/sdk/resources/proto/training.proto
snet/sdk/resources/proto/training_daemon.proto
snet/sdk/resources/proto/training_daemon_pb2.py
snet/sdk/resources/proto/training_daemon_pb2_grpc.py
snet/sdk/resources/proto/training_pb2.py
snet/sdk/resources/proto/training_pb2_grpc.py
snet/sdk/resources/proto/training/training.proto
snet/sdk/storage_provider/__init__.py
snet/sdk/storage_provider/service_metadata.py
snet/sdk/storage_provider/storage_provider.py
snet/sdk/training/exceptions.py
snet/sdk/training/responses.py
snet/sdk/training/training.py
snet/sdk/utils/__init__.py
snet/sdk/utils/call_utils.py
snet/sdk/utils/ipfs_utils.py
snet/sdk/utils/utils.py
snet_sdk-5.0.0.dist-info/LICENSE
snet_sdk-5.0.0.dist-info/METADATA
snet_sdk-5.0.0.dist-info/WHEEL
snet_sdk-5.0.0.dist-info/namespace_packages.txt
snet_sdk-5.0.0.dist-info/top_level.txt
snet_sdk-5.0.0.dist-info/RECORD
