Metadata-Version: 2.1
Name: snet-sdk
Version: 5.0.0
Summary: SingularityNET Python SDK
Home-page: https://github.com/singnet/snet-sdk-python
Author: SingularityNET Foundation
Author-email: info@singularitynet.io
License: MIT
Requires-Python: >=3.10
License-File: LICENSE
Requires-Dist: protobuf==5.*
Requires-Dist: grpcio-tools>=1.71.0
Requires-Dist: wheel>=0.45.0
Requires-Dist: rlp>=4.1.0
Requires-Dist: web3==7.*
Requires-Dist: ipfshttpclient==0.4.13
Requires-Dist: rfc3986>=2.0.0
Requires-Dist: base58>=2.1.1
Requires-Dist: grpcio-health-checking>=1.71.0
Requires-Dist: snet-contracts==1.0.1
Requires-Dist: lighthouseweb3>=0.1.4
Requires-Dist: pymultihash==0.*
